{"data":{"markdownRemark":{"html":"<h1>欲望与理性</h1>\n<h2>信息渴求</h2>\n<blockquote>\n<p>吾常闻，非人勤以求知，乃知者勤以求人也。然吾知其谬。其知者非求人，实乃出而逐人矣</p>\n</blockquote>\n<p>知乎,抖音等无时无刻的不将信息推过来,白鼠为了追求快感会不停的按动电门直到饿死,我们现在也处在相同的处境.信息会自动从密度高的地方渗透到密度低的地方,人对信息的渴求,这都是是天性而不是问题.问题就在于如何控制.</p>\n<p>往清水中加盐水如何让水不变?这是不可能的(2333).唯一的办法就是提升水本来的盐度.简单的讲就是如果不想自己沉迷手机就要找到其他的能够满足自己的信息源.</p>\n<p>大自然或者讲现实世界就是最好的信息源,要能够从中获得更多的信息.同样是古镇旅游,开启自动巡航模式的手机玩家,前来采风的艺术生,民间风俗教授 三者的信息获取能力定然不同.上课时睡觉,为什么有人昏昏欲睡有人津津有味?信息的获取能力不一样.无聊的程度实际上就是获取信息的程度,所以想要戒除廉价而无用的信息糖果一个可行的办法就是想办法增加自己获取信息的能力,举例来讲就是植物学,透视学等可以从大自然中获得更多的信息,语言学可以从单纯的记忆背诵外语中获得更多的信息.</p>"}},"pageContext":{"isCreatedByStatefulCreatePages":false,"slug":"/talk/自控/"}}