{"data":{"markdownRemark":{"html":"<p>此处收集一些TS的豆知识</p>\n<h3>构造器带修饰符自动赋值</h3>\n<p><a href=\"https://kendaleiv.com/typescript-constructor-assignment-public-and-private-keywords/\">https://kendaleiv.com/typescript-constructor-assignment-public-and-private-keywords/</a></p>\n<div class=\"gatsby-highlight\" data-language=\"typescript\"><pre style=\"counter-reset: linenumber NaN\" class=\"language-typescript line-numbers\"><code class=\"language-typescript\"><span class=\"token keyword\">class</span> <span class=\"token class-name\">TestClass</span> <span class=\"token punctuation\">{</span>\n  <span class=\"token keyword\">private</span> name<span class=\"token punctuation\">:</span> <span class=\"token builtin\">string</span><span class=\"token punctuation\">;</span>\n\n  <span class=\"token keyword\">constructor</span><span class=\"token punctuation\">(</span><span class=\"token parameter\">name<span class=\"token punctuation\">:</span> <span class=\"token builtin\">string</span></span><span class=\"token punctuation\">)</span> <span class=\"token punctuation\">{</span>\n    <span class=\"token keyword\">this</span><span class=\"token punctuation\">.</span>name <span class=\"token operator\">=</span> name<span class=\"token punctuation\">;</span>\n  <span class=\"token punctuation\">}</span>\n<span class=\"token punctuation\">}</span></code><span aria-hidden=\"true\" class=\"line-numbers-rows\" style=\"white-space: normal; width: auto; left: 0;\"><span></span><span></span><span></span><span></span><span></span><span></span><span></span></span></pre></div>\n<div class=\"gatsby-highlight\" data-language=\"typescript\"><pre style=\"counter-reset: linenumber NaN\" class=\"language-typescript line-numbers\"><code class=\"language-typescript\"><span class=\"token keyword\">class</span> <span class=\"token class-name\">TestClass</span> <span class=\"token punctuation\">{</span>\n  <span class=\"token keyword\">constructor</span><span class=\"token punctuation\">(</span><span class=\"token parameter\"><span class=\"token keyword\">private</span> name<span class=\"token punctuation\">:</span> <span class=\"token builtin\">string</span></span><span class=\"token punctuation\">)</span> <span class=\"token punctuation\">{</span> <span class=\"token punctuation\">}</span>\n<span class=\"token punctuation\">}</span></code><span aria-hidden=\"true\" class=\"line-numbers-rows\" style=\"white-space: normal; width: auto; left: 0;\"><span></span><span></span><span></span></span></pre></div>\n<p>这两段代码是等价的</p>","fields":{"slug":"/share/ts/","disqus":{"shortname":"woodgear-blog"}},"frontmatter":{"id":"524e37","time":"2020-10-20T16:07:43+08:00","tag":null},"parent":{"__typename":"File","name":"ts","ext":".md","birthTime":"1970-01-01T00:00:00.000Z","changeTime":"2020-11-26T15:05:48.118Z","relativeDirectory":"share","absolutePath":"/home/oaa/sm/ns/share/blog/share/ts.md"}}},"pageContext":{"isCreatedByStatefulCreatePages":false,"slug":"/share/ts/","disqus":{"shortname":"woodgear-blog"}}}