{"data":{"markdownRemark":{"html":"<blockquote>\n<p>当我们从编程语言的角度考虑 一些语法糖是我们迫切需要的</p>\n</blockquote>\n<h1>init given size vec with generater function</h1>\n<h2>rust</h2>\n<div class=\"gatsby-highlight\" data-language=\"rust\"><pre style=\"counter-reset: linenumber NaN\" class=\"language-rust line-numbers\"><code class=\"language-rust\"> <span class=\"token keyword\">let</span> res<span class=\"token punctuation\">:</span>Vec<span class=\"token operator\">&lt;</span>T<span class=\"token operator\">></span> <span class=\"token operator\">=</span> <span class=\"token punctuation\">(</span><span class=\"token number\">1</span><span class=\"token punctuation\">..</span><span class=\"token number\">11</span><span class=\"token punctuation\">)</span><span class=\"token punctuation\">.</span><span class=\"token function\">map</span><span class=\"token punctuation\">(</span><span class=\"token operator\">|</span>_<span class=\"token operator\">|</span> T<span class=\"token punctuation\">:</span><span class=\"token punctuation\">:</span><span class=\"token function\">new</span><span class=\"token punctuation\">(</span><span class=\"token punctuation\">)</span><span class=\"token punctuation\">)</span><span class=\"token punctuation\">.</span><span class=\"token function\">collect</span><span class=\"token punctuation\">(</span><span class=\"token punctuation\">)</span><span class=\"token punctuation\">;</span> </code><span aria-hidden=\"true\" class=\"line-numbers-rows\" style=\"white-space: normal; width: auto; left: 0;\"><span></span></span></pre></div>\n<p> 不是很优雅</p>"}},"pageContext":{"isCreatedByStatefulCreatePages":false,"slug":"/talk\\编程语言须知/语言要素/"}}